Workbook

Sheet Executive Summary
A1: Apex Components Group
A2: FY26 Sales & Operations Forecast
A4: Executive Summary
A6: KPI | B6: Value
A7: Total Forecast Revenue | B7: =SUM('Sales Forecast'!E6:E17) -> 503625
A8: Total Forecast Quantity | B8: =SUM('Sales Forecast'!C6:C17) -> 11850
A9: Total Forecast Margin | B9: =SUM('Sales Forecast'!G6:G17) -> 171825
A10: Average Unit Price | B10: =AVERAGE('Sales Forecast'!D6:D17) -> 42.5
A11: Revenue Growth Target | B11: =Assumptions!B8 -> 0.08

Sheet Sales Forecast
A5: Month | B5: Product | C5: Forecast Quantity | D5: Unit Price | E5: Forecast Revenue | F5: Unit Cost | G5: Forecast Margin
A6: 46113 | B6: AC-100 | C6: 850 | D6: 42.5 | E6: =C6*D6 -> 36125 | F6: 28 | G6: =(D6-F6)*C6 -> 12325
A7: 46143 | B7: AC-100 | C7: 875 | D7: 42.5 | E7: =C7*D7 -> 37187.5 | F7: 28 | G7: =(D7-F7)*C7 -> 12687.5
A8: 46174 | B8: AC-100 | C8: 900 | D8: 42.5 | E8: =C8*D8 -> 38250 | F8: 28 | G8: =(D8-F8)*C8 -> 13050
A9: 46204 | B9: AC-100 | C9: 925 | D9: 42.5 | E9: =C9*D9 -> 39312.5 | F9: 28 | G9: =(D9-F9)*C9 -> 13412.5
A10: 46235 | B10: AC-100 | C10: 950 | D10: 42.5 | E10: =C10*D10 -> 40375 | F10: 28 | G10: =(D10-F10)*C10 -> 13775
A11: 46266 | B11: AC-100 | C11: 975 | D11: 42.5 | E11: =C11*D11 -> 41437.5 | F11: 28 | G11: =(D11-F11)*C11 -> 14137.5
A12: 46296 | B12: AC-100 | C12: 1000 | D12: 42.5 | E12: =C12*D12 -> 42500 | F12: 28 | G12: =(D12-F12)*C12 -> 14500
A13: 46327 | B13: AC-100 | C13: 1025 | D13: 42.5 | E13: =C13*D13 -> 43562.5 | F13: 28 | G13: =(D13-F13)*C13 -> 14862.5
A14: 46357 | B14: AC-100 | C14: 1050 | D14: 42.5 | E14: =C14*D14 -> 44625 | F14: 28 | G14: =(D14-F14)*C14 -> 15225
A15: 46388 | B15: AC-100 | C15: 1075 | D15: 42.5 | E15: =C15*D15 -> 45687.5 | F15: 28 | G15: =(D15-F15)*C15 -> 15587.5
A16: 46419 | B16: AC-100 | C16: 1100 | D16: 42.5 | E16: =C16*D16 -> 46750 | F16: 28 | G16: =(D16-F16)*C16 -> 15950
A17: 46447 | B17: AC-100 | C17: 1125 | D17: 42.5 | E17: =C17*D17 -> 47812.5 | F17: 28 | G17: =(D17-F17)*C17 -> 16312.5

Sheet Customer Orders
A1: Apex Components Group
A2: FY26 Customer Orders
A4: Customer Order Register
A6: Order ID | B6: Order Line | C6: Customer Name | D6: Product Code | E6: Quantity | F6: Unit Price | G6: Order Value | H6: Order Date | I6: Required Date | J6: Order Status
A7: ORD0001 | B7: 1 | C7: Northstar Engineering | D7: AC-100 | E7: 125 | F7: 42.5 | G7: =E7*F7 -> 5312.5 | H7: 46113 | I7: 46134 | J7: Confirmed
A8: ORD0002 | B8: 1 | C8: Meridian Systems | D8: AC-120 | E8: 75 | F8: 67 | G8: =E8*F8 -> 5025 | H8: 46115 | I8: 46143 | J8: Confirmed
A9: ORD0003 | B9: 1 | C9: Hartwell Manufacturing | D9: AC-110 | E9: 240 | F9: 18.75 | G9: =E9*F9 -> 4500 | H9: 46118 | I9: 46132 | J9: Shipped
A10: ORD0004 | B10: 1 | C10: Northstar Engineering | D10: AC-140 | E10: 90 | F10: 24.25 | G10: =E10*F10 -> 2182.5 | H10: 46120 | I10: 46134 | J10: Confirmed
A11: ORD0004 | B11: 2 | C11: Northstar Engineering | D11: AC-170 | E11: 150 | F11: 15.75 | G11: =E11*F11 -> 2362.5 | H11: 46120 | I11: 46134 | J11: Confirmed
A12: ORD0005 | B12: 1 | C12: Beacon Industrial | D12: AC-130 | E12: 60 | F12: 85.5 | G12: =E12*F12 -> 5130 | H12: 46122 | I12: 46157 | J12: Pending
A13: ORD0006 | B13: 1 | C13: Vector Dynamics | D13: AC-150 | E13: 35 | F13: 112 | G13: =E13*F13 -> 3920 | H13: 46125 | I13: 46167 | J13: Confirmed
A14: ORD0007 | B14: 1 | C14: Meridian Systems | D14: AC-160 | E14: 180 | F14: 31.5 | G14: =E14*F14 -> 5670 | H14: 46127 | I14: 46148 | J14: Shipped
A15: ORD0008 | B15: 1 | C15: Hartwell Manufacturing | D15: AC-180 | E15: 110 | F15: 38 | G15: =E15*F15 -> 4180 | H15: 46129 | I15: 46150 | J15: Confirmed
A16: ORD0009 | B16: 1 | C16: Beacon Industrial | D16: AC-190 | E16: 50 | F16: 94.5 | G16: =E16*F16 -> 4725 | H16: 46132 | I16: 46167 | J16: Pending

Sheet Product Master
A1: Apex Components Group
A2: Product Master
A4: Active Product Catalogue
A6: Product Code | B6: Product Description | C6: Product Category | D6: Standard Unit Price | E6: Standard Unit Cost | F6: Lead Time Days | G6: Product Status
A7: AC-100 | B7: Precision Housing | C7: Housings | D7: 42.5 | E7: 28 | F7: 21 | G7: Active
A8: AC-110 | B8: Mounting Bracket | C8: Brackets | D8: 18.75 | E8: 11.5 | F8: 14 | G8: Active
A9: AC-120 | B9: Drive Coupling | C9: Couplings | D9: 67 | E9: 44.5 | F9: 28 | G9: Active
A10: AC-130 | B10: Bearing Assembly | C10: Assemblies | D10: 85.5 | E10: 57 | F10: 35 | G10: Active
A11: AC-140 | B11: Seal Kit | C11: Service Kits | D11: 24.25 | E11: 14.75 | F11: 14 | G11: Active
A12: AC-150 | B12: Support Frame | C12: Frames | D12: 112 | E12: 76 | F12: 42 | G12: Active
A13: AC-160 | B13: Retaining Plate | C13: Plates | D13: 31.5 | E13: 19.25 | F13: 21 | G13: Active
A14: AC-170 | B14: Shaft Collar | C14: Components | D14: 15.75 | E14: 9.5 | F14: 14 | G14: Active
A15: AC-180 | B15: Housing Cover | C15: Housings | D15: 38 | E15: 24 | F15: 21 | G15: Active
A16: AC-190 | B16: Link Assembly | C16: Assemblies | D16: 94.5 | E16: 63.5 | F16: 35 | G16: Active
A17: 20010 | B17: Legacy Spacer | C17: Components | D17: 12 | E17: 7.25 | F17: 14 | G17: Legacy
A18: 30025 | B18: Legacy Clamp | C18: Brackets | D18: 16.5 | E18: 10 | F18: 14 | G18: Legacy

Sheet Assumptions
A1: Apex Components Group
A2: FY26 Sales & Operations Forecast
A4: Planning Assumptions
A6: Assumption | B6: Value | C6: Notes
A7: Standard Working Days | B7: 250 | C7: Annual planning assumption
A8: Revenue Growth Target | B8: 0.08 | C8: FY26 target
A9: Gross Margin Target | B9: 0.32 | C9: Target gross margin
A10: Forecast Tolerance | B10: 0.05 | C10: Variance requiring review
A11: Default Lead Time (Days) | B11: 21 | C11: Standard customer order lead time

Sheet Calc_Helper
A1: Apex Components Group
A2: Supporting Calculations
A4: Forecast Metrics
A6: Metric | B6: Value
A7: Forecast Revenue | B7: =SUM('Sales Forecast'!E6:E17) -> 503625
A8: Forecast Quantity | B8: =SUM('Sales Forecast'!C6:C17) -> 11850
A9: Forecast Margin | B9: =SUM('Sales Forecast'!G6:G17) -> 171825
A10: Average Margin % | B10: =B9/B7 -> 0.34117647
